txtelegraf/__init__.py
txtelegraf/measurement.py
txtelegraf/tcp.py
txtelegraf/udp.py
txtelegraf-0.3.0.dist-info/LICENSE.txt
txtelegraf-0.3.0.dist-info/METADATA
txtelegraf-0.3.0.dist-info/WHEEL
txtelegraf-0.3.0.dist-info/top_level.txt
txtelegraf-0.3.0.dist-info/RECORD
