Metadata-Version: 2.1
Name: txtelegraf
Version: 0.3.0
Summary: A TCP/UDP Telegraf/InfluxDB client for Twisted.
Home-page: https://github.com/offero/txtelegraf
Author: Christopher Kirkos
Author-email: offero@gmail.com
License: Apache License 2.0
Download-URL: https://github.com/offero/txtelegraf/archive/v0.3.0.zip
Keywords: twisted,telegraf,influxdb
Platform: UNKNOWN
Classifier: Development Status :: 5 - Production/Stable
Classifier: Intended Audience :: Developers
Classifier: Operating System :: OS Independent
Classifier: License :: OSI Approved :: Apache Software License
Classifier: Programming Language :: Python
Classifier: Programming Language :: Python :: 2.7
Classifier: Programming Language :: Python :: 3.6
Classifier: Programming Language :: Python :: 3.7
Classifier: Programming Language :: Python :: Implementation :: PyPy
Requires-Dist: twisted
Requires-Dist: six
